hydrobm/__init__.py
hydrobm/_version.py
hydrobm/benchmarks.py
hydrobm/calculate.py
hydrobm/metrics.py
hydrobm/utils.py
hydrobm/tests/__init__.py
hydrobm/tests/conftest.py
hydrobm/tests/test_benchmarks.py
hydrobm/tests/test_metrics.py
hydrobm/tests/test_utils.py
hydrobm-1.0.2.dist-info/AUTHORS.rst
hydrobm-1.0.2.dist-info/LICENSE
hydrobm-1.0.2.dist-info/METADATA
hydrobm-1.0.2.dist-info/WHEEL
hydrobm-1.0.2.dist-info/top_level.txt
hydrobm-1.0.2.dist-info/RECORD
