Metadata-Version: 2.1
Name: hydrobm
Version: 1.0.2
Summary: Python package for calculating simple benchmarks from hydroclimatic timeseries
Home-page: https://github.com/wknoben/hydrobm
Author: Wouter Knoben
Author-email: wouter.knoben@ucalgary.ca
License: GPLv3
Classifier: Development Status :: 5 - Production/Stable
Classifier: Natural Language :: English
Classifier: Programming Language :: Python :: 3
Requires-Python: >=3.8
License-File: LICENSE
License-File: AUTHORS.rst
Requires-Dist: numpy
Requires-Dist: pandas
Requires-Dist: scipy
Requires-Dist: xarray
